test/__init__.py
test/test_xbow_spot_pool.py
xbow/__init__.py
xbow/_version.py
xbow/commands.py
xbow/configuration.py
xbow/data.py
xbow/filesystems.py
xbow/instances.py
xbow/metering.py
xbow/pools.py
xbow/utilities.py
xbow-0.6.3.1.data/scripts/xbow
xbow-0.6.3.1.data/scripts/xbow-check
xbow-0.6.3.1.data/scripts/xbow-config
xbow-0.6.3.1.data/scripts/xbow-configure
xbow-0.6.3.1.data/scripts/xbow-create_cluster
xbow-0.6.3.1.data/scripts/xbow-create_filesystem
xbow-0.6.3.1.data/scripts/xbow-delete_cluster
xbow-0.6.3.1.data/scripts/xbow-delete_filesystem
xbow-0.6.3.1.data/scripts/xbow-delete_workers
xbow-0.6.3.1.data/scripts/xbow-exec
xbow-0.6.3.1.data/scripts/xbow-fetch
xbow-0.6.3.1.data/scripts/xbow-hostname
xbow-0.6.3.1.data/scripts/xbow-launch
xbow-0.6.3.1.data/scripts/xbow-login
xbow-0.6.3.1.data/scripts/xbow-notebook
xbow-0.6.3.1.data/scripts/xbow-portal
xbow-0.6.3.1.data/scripts/xbow-provision
xbow-0.6.3.1.data/scripts/xbow-run
xbow-0.6.3.1.data/scripts/xbow-submit
xbow-0.6.3.1.data/scripts/xbow-sync
xbow-0.6.3.1.dist-info/LICENSE.txt
xbow-0.6.3.1.dist-info/METADATA
xbow-0.6.3.1.dist-info/WHEEL
xbow-0.6.3.1.dist-info/top_level.txt
xbow-0.6.3.1.dist-info/RECORD
