Metadata-Version: 2.1
Name: xbow
Version: 0.6.3.1
Summary: Longbow in the cloud
Home-page: UNKNOWN
Author: Christian Suess, Charlie Laughton
Author-email: christian.suess1@nottingham.ac.uk, charles.laughton@nottingham.ac.uk
License: MIT license.
Platform: UNKNOWN
Classifier: Development Status :: 3 - Alpha
Classifier: Intended Audience :: Science/Research
Classifier: Environment :: Console
Classifier: License :: OSI Approved :: MIT License
Classifier: Programming Language :: Python
Classifier: Programming Language :: Python :: 2
Classifier: Programming Language :: Python :: 2.7
Classifier: Programming Language :: Python :: 3
Classifier: Programming Language :: Python :: 3.4
Classifier: Programming Language :: Python :: 3.5
Classifier: Programming Language :: Python :: 3.6
Classifier: Topic :: Scientific/Engineering
Classifier: Operating System :: MacOS :: MacOS X
Classifier: Operating System :: POSIX
Classifier: Operating System :: Unix
Requires-Dist: boto3
Requires-Dist: paramiko
Requires-Dist: cryptography (>=2.5)
Requires-Dist: pyYAML
